ass2/generated/ALU.v
module ALU(
  input         clock,
  input         reset,
  input  [31:0] io_op1,
  input  [31:0] io_op2,
  input  [3:0]  io_sel,
  output [31:0] io_result,
  output        io_cmpResult
);
  wire  _T = 4'h0 == io_sel; // @[Conditional.scala 37:30]
  wire [31:0] _T_2 = io_op1 + io_op2; // @[ALU.scala 19:36]
  wire  _T_3 = 4'h1 == io_sel; // @[Conditional.scala 37:30]
  wire [31:0] _T_5 = io_op1 - io_op2; // @[ALU.scala 20:36]
  wire  _T_6 = 4'h2 == io_sel; // @[Conditional.scala 37:30]
  wire [63:0] _T_7 = io_op1 * io_op2; // @[ALU.scala 21:36]
  wire  _T_8 = 4'h3 == io_sel; // @[Conditional.scala 37:30]
  wire [31:0] _T_10 = io_op1 + 32'h1; // @[ALU.scala 22:36]
  wire  _T_11 = 4'h4 == io_sel; // @[Conditional.scala 37:30]
  wire [31:0] _T_13 = io_op1 - 32'h1; // @[ALU.scala 23:36]
  wire  _T_14 = 4'h5 == io_sel; // @[Conditional.scala 37:30]
  wire [31:0] _T_15 = ~io_op1; // @[ALU.scala 24:29]
  wire  _T_16 = 4'h6 == io_sel; // @[Conditional.scala 37:30]
  wire [31:0] _T_17 = io_op1 & io_op2; // @[ALU.scala 25:36]
  wire  _T_18 = 4'h7 == io_sel; // @[Conditional.scala 37:30]
  wire [31:0] _T_19 = io_op1 | io_op2; // @[ALU.scala 26:36]
  wire  _T_20 = 4'h8 == io_sel; // @[Conditional.scala 37:30]
  wire [31:0] _T_21 = io_op1 ^ io_op2; // @[ALU.scala 27:36]
  wire  _T_22 = 4'h9 == io_sel; // @[Conditional.scala 37:30]
  wire  _T_23 = io_op1 == io_op2; // @[ALU.scala 30:39]
  wire  _T_24 = 4'ha == io_sel; // @[Conditional.scala 37:30]
  wire  _T_25 = io_op1 != io_op2; // @[ALU.scala 31:40]
  wire  _T_26 = 4'hb == io_sel; // @[Conditional.scala 37:30]
  wire  _T_27 = io_op1 > io_op2; // @[ALU.scala 32:40]
  wire  _T_28 = 4'hc == io_sel; // @[Conditional.scala 37:30]
  wire  _T_29 = io_op1 >= io_op2; // @[ALU.scala 33:40]
  wire  _T_30 = 4'hd == io_sel; // @[Conditional.scala 37:30]
  wire  _T_31 = io_op1 < io_op2; // @[ALU.scala 34:40]
  wire  _T_32 = 4'he == io_sel; // @[Conditional.scala 37:30]
  wire  _T_33 = io_op1 <= io_op2; // @[ALU.scala 35:40]
  wire  _T_34 = 4'hf == io_sel; // @[Conditional.scala 37:30]
  wire  _GEN_1 = _T_32 ? _T_33 : _T_34; // @[Conditional.scala 39:67]
  wire  _GEN_2 = _T_30 ? _T_31 : _GEN_1; // @[Conditional.scala 39:67]
  wire  _GEN_3 = _T_28 ? _T_29 : _GEN_2; // @[Conditional.scala 39:67]
  wire  _GEN_4 = _T_26 ? _T_27 : _GEN_3; // @[Conditional.scala 39:67]
  wire  _GEN_5 = _T_24 ? _T_25 : _GEN_4; // @[Conditional.scala 39:67]
  wire  _GEN_6 = _T_22 ? _T_23 : _GEN_5; // @[Conditional.scala 39:67]
  wire [31:0] _GEN_7 = _T_20 ? _T_21 : 32'h0; // @[Conditional.scala 39:67]
  wire  _GEN_8 = _T_20 ? 1'h0 : _GEN_6; // @[Conditional.scala 39:67]
  wire [31:0] _GEN_9 = _T_18 ? _T_19 : _GEN_7; // @[Conditional.scala 39:67]
  wire  _GEN_10 = _T_18 ? 1'h0 : _GEN_8; // @[Conditional.scala 39:67]
  wire [31:0] _GEN_11 = _T_16 ? _T_17 : _GEN_9; // @[Conditional.scala 39:67]
  wire  _GEN_12 = _T_16 ? 1'h0 : _GEN_10; // @[Conditional.scala 39:67]
  wire [31:0] _GEN_13 = _T_14 ? _T_15 : _GEN_11; // @[Conditional.scala 39:67]
  wire  _GEN_14 = _T_14 ? 1'h0 : _GEN_12; // @[Conditional.scala 39:67]
  wire [31:0] _GEN_15 = _T_11 ? _T_13 : _GEN_13; // @[Conditional.scala 39:67]
  wire  _GEN_16 = _T_11 ? 1'h0 : _GEN_14; // @[Conditional.scala 39:67]
  wire [31:0] _GEN_17 = _T_8 ? _T_10 : _GEN_15; // @[Conditional.scala 39:67]
  wire  _GEN_18 = _T_8 ? 1'h0 : _GEN_16; // @[Conditional.scala 39:67]
  wire [63:0] _GEN_19 = _T_6 ? _T_7 : {{32'd0}, _GEN_17}; // @[Conditional.scala 39:67]
  wire  _GEN_20 = _T_6 ? 1'h0 : _GEN_18; // @[Conditional.scala 39:67]
  wire [63:0] _GEN_21 = _T_3 ? {{32'd0}, _T_5} : _GEN_19; // @[Conditional.scala 39:67]
  wire  _GEN_22 = _T_3 ? 1'h0 : _GEN_20; // @[Conditional.scala 39:67]
  wire [63:0] _GEN_23 = _T ? {{32'd0}, _T_2} : _GEN_21; // @[Conditional.scala 40:58]
  assign io_result = _GEN_23[31:0]; // @[ALU.scala 14:13 ALU.scala 19:26 ALU.scala 20:26 ALU.scala 21:26 ALU.scala 22:26 ALU.scala 23:26 ALU.scala 24:26 ALU.scala 25:26 ALU.scala 26:26 ALU.scala 27:26]
  assign io_cmpResult = _T ? 1'h0 : _GEN_22; // @[ALU.scala 15:16 ALU.scala 30:29 ALU.scala 31:30 ALU.scala 32:30 ALU.scala 33:30 ALU.scala 34:30 ALU.scala 35:30 ALU.scala 36:30]
endmodule

ass2/generated/ALU.vcd
$date
2022-11-05T17:51+0000
$end
$version
0.2
$end
$comment

$end
$timescale 1ns  $end
$scope module ALU $end
 $var wire 1 ! _GEN_22 $end
 $var wire 1 " _GEN_16 $end
 $var wire 1 # _GEN_2 $end
 $var wire 1 $ _GEN_10 $end
 $var wire 1 % _T $end
 $var wire 64 & _GEN_19 $end
 $var wire 1 ' _GEN_5 $end
 $var wire 32 ( _GEN_13 $end
 $var wire 1 ) _GEN_8 $end
 $var wire 32 * io_op1 $end
 $var wire 4 + io_sel $end
 $var wire 1 , _GEN_12 $end
 $var wire 32 - _GEN_15 $end
 $var wire 32 . _GEN_7 $end
 $var wire 64 / _GEN_21 $end
 $var wire 1 0 _GEN_18 $end
 $var wire 1 1 _GEN_1 $end
 $var wire 1 2 _GEN_4 $end
 $var wire 1 3 clock $end
 $var wire 1 4 io_cmpResult $end
 $var wire 64 5 _GEN_23 $end
 $var wire 32 6 io_result $end
 $var wire 32 7 _GEN_17 $end
 $var wire 32 8 _GEN_11 $end
 $var wire 1 9 _GEN_20 $end
 $var wire 1 : _GEN_14 $end
 $var wire 1 ; _GEN_6 $end
 $var wire 32 < _GEN_9 $end
 $var wire 32 = io_op2 $end
 $var wire 1 > reset $end
 $var wire 1 ? _GEN_3 $end
$upscope $end
$enddefinitions $end
$dumpvars
0%
b00000000000000000000000000000000 <
0;
b00000000000000000000000000000000 =
b0000000000000000000000000000000000000000000000000000000000000000 5
0'
b00000000000000000000000000000000 (
0>
b00000000000000000000000000000000 7
b0000000000000000000000000000000000000000000000000000000000000000 /
0!
b00000000000000000000000000000000 8
0"
0#
09
0:
02
03
04
b00000000000000000000000000000000 6
b00000000000000000000000000000000 .
b0000000000000000000000000000000000000000000000000000000000000000 &
00
01
b00000000000000000000000000000000 *
0)
b0000 +
0?
0,
b00000000000000000000000000000000 -
0$
$end
#0
1%
1>
#1
13
#6
03
#11
13
#16
03
#21
13
#26
03
#31
13
#36
03
#41
13
#46
03
b0000000000000000000000000000000000000000000000000000000000000100 5
b00000000000000000000000000000010 *
b00000000000000000000000000000100 6
b00000000000000000000000000000010 =
0>
#51
13
#56
03
#61
13
#66
03
#71
13
#76
03
#81
13
#86
03
#91
13
#96
03
0%
b0000000000000000000000000000000000000000000000000000000000000011 5
b00000000000000000000000000000110 *
b00000000000000000000000000000011 6
b0001 +
b00000000000000000000000000000011 =
b0000000000000000000000000000000000000000000000000000000000000011 /
#101
13
#106
03
#111
13
#116
03
#121
13
#126
03
#131
13
#136
03
#141
13
#146
03
b0000000000000000000000000000000000000000000000000000000000001001 &
b0000000000000000000000000000000000000000000000000000000000001001 5
b00000000000000000000000000000011 *
b00000000000000000000000000001001 6
b0010 +
b0000000000000000000000000000000000000000000000000000000000001001 /
#151
13
#156
03
#161
13
#166
03
#171
13
#176
03
#181
13
#186
03
#191
13
#196
03
b0000000000000000000000000000000000000000000000000000000000000101 &
b0000000000000000000000000000000000000000000000000000000000000101 5
b00000000000000000000000000000100 *
b00000000000000000000000000000101 6
b0011 +
b00000000000000000000000000001010 =
b00000000000000000000000000000101 7
b0000000000000000000000000000000000000000000000000000000000000101 /
#201
13
#206
03
#211
13
#216
03
#221
13
#226
03
#231
13
#236
03
#241
13
#246
03
b00000000000000000000000000000010 -
b0000000000000000000000000000000000000000000000000000000000000010 &
b0000000000000000000000000000000000000000000000000000000000000010 5
b00000000000000000000000000000011 *
b00000000000000000000000000000010 6
b0100 +
b00000000000000000000000000000010 7
b0000000000000000000000000000000000000000000000000000000000000010 /
#251
13
#256
03
#261
13
#266
03
#271
13
#276
03
#281
13
#286
03
#291
13
#296
03
b11111111111111111111111111111111 -
b0000000000000000000000000000000011111111111111111111111111111111 &
b0000000000000000000000000000000011111111111111111111111111111111 5
b00000000000000000000000000000000 *
b11111111111111111111111111111111 6
b0101 +
b00000000000000000000000000010110 =
b11111111111111111111111111111111 (
b11111111111111111111111111111111 7
b0000000000000000000000000000000011111111111111111111111111111111 /
#301
13
#306
03
#311
13
#316
03
#321
13
#326
03
#331
13
#336
03
#341
13
#346
03
b00000000000000000000000000001000 -
b00000000000000000000000000001000 8
b0000000000000000000000000000000000000000000000000000000000001000 &
b0000000000000000000000000000000000000000000000000000000000001000 5
b00000000000000000000000000001001 *
b00000000000000000000000000001000 6
b0110 +
b00000000000000000000000000001110 =
b00000000000000000000000000001000 (
b00000000000000000000000000001000 7
b0000000000000000000000000000000000000000000000000000000000001000 /
#351
13
#356
03
#361
13
#366
03
#371
13
#376
03
#381
13
#386
03
#391
13
#396
03
b00000000000000000000000000001111 -
b00000000000000000000000000001111 <
b00000000000000000000000000001111 8
b0000000000000000000000000000000000000000000000000000000000001111 &
b0000000000000000000000000000000000000000000000000000000000001111 5
b00000000000000000000000000001111 6
b0111 +
b00000000000000000000000000001111 (
b00000000000000000000000000001111 7
b0000000000000000000000000000000000000000000000000000000000001111 /
#401
13
#406
03
#411
13
#416
03
#421
13
#426
03
#431
13
#436
03
#441
13
#446
03
b00000000000000000000000000000111 -
b00000000000000000000000000000111 <
b00000000000000000000000000000111 .
b00000000000000000000000000000111 8
b0000000000000000000000000000000000000000000000000000000000000111 &
b0000000000000000000000000000000000000000000000000000000000000111 5
b00000000000000000000000000000111 6
b1000 +
b00000000000000000000000000000111 (
b00000000000000000000000000000111 7
b0000000000000000000000000000000000000000000000000000000000000111 /
#451
13
#456
03
#461
13
#466
03
#471
13
#476
03
#481
13
#486
03
#491
13
#496
03
b00000000000000000000000000000000 -
b00000000000000000000000000000000 <
14
b00000000000000000000000000000000 .
b0000000000000000000000000000000000000000000000000000000000000000 &
b0000000000000000000000000000000000000000000000000000000000000000 5
b00000000000000000000000000000000 6
b00000000000000000000000000000100 =
b00000000000000000000000000000000 (
b00000000000000000000000000000000 7
b0000000000000000000000000000000000000000000000000000000000000000 /
1)
1!
10
1"
b00000000000000000000000000000000 8
b00000000000000000000000000000100 *
19
1$
b1001 +
1:
1,
1;
#501
13
#506
03
#511
13
#516
03
#521
13
#526
03
#531
13
#536
03
#541
13
#546
03
00
0!
0"
04
09
0$
b00000000000000000000000000000101 =
0:
0,
0;
0)
#551
13
#556
03
#561
13
#566
03
#571
13
#576
03
#581
13
#586
03
#591
13
#596
03
14
1'
b00000000000000000000000000000001 =
1)
1!
10
1"
b00000000000000000000000000000110 *
19
1$
b1010 +
1:
1,
1;
#601
13
#606
03
#611
13
#616
03
#621
13
#626
03
#631
13
#636
03
#641
13
#646
03
00
0!
0"
04
0'
0$
09
b00000000000000000000000000000110 =
0:
0,
0;
0)
#651
13
#656
03
#661
13
#666
03
#671
13
#676
03
#681
13
#686
03
#691
13
#696
03
14
1'
b00000000000000000000000000000111 =
1)
1!
10
1"
12
b00000000000000000000000000001000 *
19
1$
b1011 +
1:
1,
1;
#701
13
#706
03
#711
13
#716
03
#721
13
#726
03
#731
13
#736
03
#741
13
#746
03
04
0'
b00000000000000000000000000001000 =
0)
0!
00
0"
02
09
0$
0:
0,
0;
#751
13
#756
03
#761
13
#766
03
#771
13
#776
03
#781
13
#786
03
#791
13
#796
03
14
1'
b00000000000000000000000000000111 =
1)
1!
10
1?
1"
12
b00000000000000000000000000000111 *
19
1$
b1100 +
1:
1,
1;
#801
13
#806
03
#811
13
#816
03
#821
13
#826
03
#831
13
#836
03
#841
13
#846
03
04
0'
b00000000000000000000000000001000 =
0)
0!
00
0?
0"
02
09
0$
0:
0,
0;
#851
13
#856
03
#861
13
#866
03
#871
13
#876
03
#881
13
#886
03
#891
13
#896
03
14
1'
b00000000000000000000000000000100 =
1)
1!
10
1?
1"
1#
12
b00000000000000000000000000000011 *
19
1$
b1101 +
1:
1,
1;
#901
13
#906
03
#911
13
#916
03
#921
13
#926
03
#931
13
#936
03
#941
13
#946
03
#951
13
#956
03
#961
13
#966
03
#971
13
#976
03
#981
13
#986
03
#991
13
#996
03
11
b1110 +
b00000000000000000000000000000011 =
#1001
13
#1006
03
#1011
13
#1016
03
#1021
13
#1026
03
#1031
13
#1036
03
#1041
13
#1046
03
04
0'
b00000000000000000000000000000001 =
0)
0!
00
0?
0"
01
0#
02
09
0$
0:
0,
0;
#1051
13
#1056
03
#1061
13
#1066
03
#1071
13
#1076
03
#1081
13
#1086
03
#1091
13
#1096
03
14
1'
b00000000000000000000000000010110 =
1)
1!
10
1?
1"
11
1#
12
b00000000000000000000000011101010 *
19
1$
b1111 +
1:
1,
1;
